microlearn/__init__.py
microlearn/offloader.py
microlearn/ml_models/GaussianNB.py
microlearn/ml_models/KMeans.py
microlearn/ml_models/LinearDiscriminantAnalysis.py
microlearn/ml_models/LinearRegression.py
microlearn/ml_models/LogisticRegression.py
microlearn/ml_models/PCA.py
microlearn/ml_models/PassiveAggressiveClassifier.py
microlearn/ml_models/Perceptron.py
microlearn/ml_models/QuadraticDiscriminantAnalysis.py
microlearn/ml_models/SVC.py
microlearn/ml_models/__init__.py
micro_learn-0.0.4.dist-info/LICENSE
micro_learn-0.0.4.dist-info/METADATA
micro_learn-0.0.4.dist-info/WHEEL
micro_learn-0.0.4.dist-info/top_level.txt
micro_learn-0.0.4.dist-info/RECORD
