Metadata-Version: 2.1
Name: micro-learn
Version: 0.0.4
Summary: A Python library to export scikit-learn models to microcontrollers
Home-page: https://github.com/adarsh1001/micro-learn
Author: Adarsh Pal Singh
Author-email: adarshpalsingh1996@gmail.com
License: UNKNOWN
Platform: UNKNOWN
Classifier: Programming Language :: Python :: 3
Classifier: License :: OSI Approved :: MIT License
Classifier: Operating System :: OS Independent
Requires-Python: >=3.6
